rustypot/__init__.py
rustypot/__init__.pyi
rustypot/py.typed
rustypot/rustypot.cpython-313-x86_64-linux-gnu.so
rustypot-1.4.1.dist-info/METADATA
rustypot-1.4.1.dist-info/WHEEL
rustypot-1.4.1.dist-info/licenses/LICENSE
rustypot-1.4.1.dist-info/RECORD
